maskinversion/__init__.py
maskinversion/maskinversion.py
maskinversion/utils.py
maskinversion_torch-1.1.dist-info/METADATA
maskinversion_torch-1.1.dist-info/WHEEL
maskinversion_torch-1.1.dist-info/top_level.txt
maskinversion_torch-1.1.dist-info/RECORD
