Metadata-Version: 2.1
Name: maskinversion-torch
Version: 1.1
Summary: MaskInversion
Home-page: https://github.com/WalBouss/MaskInversion
Author: Walid Bousselham, Sofian Chaybouti, Christian Rupprecht, Vittorio Ferrari, Hilde Kuehne
Author-email: 
Keywords: Localized Embedding,Mask,Explainability,ViT,Vision-Language Models,CLIP pretrained
Classifier: Development Status :: 3 - Alpha
Classifier: Intended Audience :: Education
Classifier: Intended Audience :: Science/Research
Classifier: License :: OSI Approved :: Apache Software License
Classifier: Programming Language :: Python :: 3.7
Classifier: Programming Language :: Python :: 3.8
Classifier: Programming Language :: Python :: 3.9
Classifier: Programming Language :: Python :: 3.10
Classifier: Topic :: Scientific/Engineering
Classifier: Topic :: Scientific/Engineering :: Artificial Intelligence
Classifier: Topic :: Software Development
Classifier: Topic :: Software Development :: Libraries
Classifier: Topic :: Software Development :: Libraries :: Python Modules
Requires-Python: >=3.7
Requires-Dist: torch >=1.11
Requires-Dist: torchvision
Requires-Dist: timm
Requires-Dist: open-clip-torch <=2.23.0
Requires-Dist: legrad-torch
Requires-Dist: opencv-python
Requires-Dist: matplotlib
Requires-Dist: numpy
Requires-Dist: requests
Requires-Dist: einops
